django_kit_fos
